base_agents.py
base_agents-0.1.1.dist-info/METADATA
base_agents-0.1.1.dist-info/WHEEL
base_agents-0.1.1.dist-info/licenses/LICENSE
base_agents-0.1.1.dist-info/RECORD
