Metadata-Version: 2.4
Name: base-agents
Version: 0.1.1
Summary: A simple way to build AI agents with tools, MCP (Model Context Protocol) tools, and sub-agents.
Project-URL: Homepage, https://github.com/HaotianShan/BaseAgents
Project-URL: Issues, https://github.com/HaotianShan/BaseAgents/issues
Author-email: Haotian Shan <haotianshan@example.com>
License: MIT
License-File: LICENSE
Keywords: agents,ai,hierarchical,langchain,llm,mcp,tools
Classifier: Development Status :: 4 - Beta
Classifier: Intended Audience :: Developers
Classifier: License :: OSI Approved :: MIT License
Classifier: Programming Language :: Python :: 3
Classifier: Programming Language :: Python :: 3.12
Classifier: Topic :: Scientific/Engineering :: Artificial Intelligence
Requires-Python: >=3.12
Requires-Dist: langchain-core>=0.3.72
Requires-Dist: langchain-mcp-adapters>=0.1.9
Requires-Dist: langchain-tools>=0.1.34
Requires-Dist: langgraph>=0.6.3
